ebd/__init__.py
ebd-0.0.38.dist-info/LICENSE
ebd-0.0.38.dist-info/METADATA
ebd-0.0.38.dist-info/WHEEL
ebd-0.0.38.dist-info/top_level.txt
ebd-0.0.38.dist-info/RECORD
